flake8/__init__.py
flake8/__main__.py
flake8/_compat.py
flake8/checker.py
flake8/defaults.py
flake8/discover_files.py
flake8/exceptions.py
flake8/processor.py
flake8/statistics.py
flake8/style_guide.py
flake8/utils.py
flake8/violation.py
flake8/api/__init__.py
flake8/api/legacy.py
flake8/formatting/__init__.py
flake8/formatting/_windows_color.py
flake8/formatting/base.py
flake8/formatting/default.py
flake8/main/__init__.py
flake8/main/application.py
flake8/main/cli.py
flake8/main/debug.py
flake8/main/options.py
flake8/options/__init__.py
flake8/options/aggregator.py
flake8/options/config.py
flake8/options/manager.py
flake8/options/parse_args.py
flake8/plugins/__init__.py
flake8/plugins/finder.py
flake8/plugins/pycodestyle.py
flake8/plugins/pyflakes.py
flake8/plugins/reporter.py
flake8-7.1.1.dist-info/LICENSE
flake8-7.1.1.dist-info/METADATA
flake8-7.1.1.dist-info/WHEEL
flake8-7.1.1.dist-info/entry_points.txt
flake8-7.1.1.dist-info/top_level.txt
flake8-7.1.1.dist-info/RECORD
