Metadata-Version: 2.1
Name: flake8
Version: 7.1.1
Summary: the modular source code checker: pep8 pyflakes and co
Home-page: https://github.com/pycqa/flake8
Author: Tarek Ziade
Author-email: tarek@ziade.org
Maintainer: Ian Stapleton Cordasco
Maintainer-email: graffatcolmingov@gmail.com
License: MIT
Classifier: Development Status :: 5 - Production/Stable
Classifier: Environment :: Console
Classifier: Framework :: Flake8
Classifier: Intended Audience :: Developers
Classifier: License :: OSI Approved :: MIT License
Classifier: Programming Language :: Python
Classifier: Programming Language :: Python :: 3
Classifier: Programming Language :: Python :: 3 :: Only
Classifier: Programming Language :: Python :: Implementation :: CPython
Classifier: Programming Language :: Python :: Implementation :: PyPy
Classifier: Topic :: Software Development :: Libraries :: Python Modules
Classifier: Topic :: Software Development :: Quality Assurance
Requires-Python: >=3.8.1
License-File: LICENSE
